<?xml version="1.0" encoding="UTF-8"?>
<MusicThread><mode>Phrygian</mode><CantusFirmus>[E4, G4, A4*, D4, F4, G4, D4, F4, G4, A4*, G4, A4*, D4, F4, E4]</CantusFirmus><middle>F4</middle><rating rate="91.66666666666667"><range>100.0</range><length>100.0</length><dominantCount>100.0</dominantCount></rating><history length="15"><PitchHistory move="1"><to>G4</to><MusicThought>Directional_Disjunct</MusicThought><exploit>false</exploit><routes><route><to>G4</to><pheromoneTrail>1685.0</pheromoneTrail></route><route><to>A4</to><pheromoneTrail>1680.0</pheromoneTrail></route><route><to>E3</to><pheromoneTrail>1552.0</pheromoneTrail></route><route><to>C4</to><pheromoneTrail>1486.0</pheromoneTrail></route><route><to>A3</to><pheromoneTrail>1482.0</pheromoneTrail></route><route><to>B3</to><pheromoneTrail>1481.0</pheromoneTrail></route></routes></PitchHistory><PitchHistory move="2"><to>A4</to><MusicThought>Directional_Conjunct</MusicThought><exploit>true</exploit><routes><route><to>A4</to><pheromoneTrail>646.0</pheromoneTrail></route></routes></PitchHistory><PitchHistory move="3"><to>D4</to><MusicThought>Complemental_LongTerm</MusicThought><exploit>true</exploit><routes><route><to>F4</to><pheromoneTrail>771.3</pheromoneTrail></route><route><to>A3</to><pheromoneTrail>695.9000000000001</pheromoneTrail></route><route><to>G4</to><pheromoneTrail>668.0</pheromoneTrail></route><route><to>E4</to><pheromoneTrail>648.7</pheromoneTrail></route><route><to>D4</to><pheromoneTrail>645.8</pheromoneTrail></route></routes></PitchHistory><PitchHistory move="4"><to>F4</to><MusicThought>Complemental_ShortTerm</MusicThought><exploit>false</exploit><routes><route><to>E4</to><pheromoneTrail>1634.66</pheromoneTrail></route><route><to>A4</to><pheromoneTrail>1240.6599999999999</pheromoneTrail></route><route><to>F4</to><pheromoneTrail>1143.44</pheromoneTrail></route><route><to>G4</to><pheromoneTrail>919.2</pheromoneTrail></route></routes></PitchHistory><PitchHistory move="5"><to>G4</to><MusicThought>Directional_Conjunct</MusicThought><exploit>true</exploit><routes><route><to>G4</to><pheromoneTrail>9304.843</pheromoneTrail></route></routes></PitchHistory><PitchHistory move="6"><to>D4</to><MusicThought>Complemental_ShortTerm</MusicThought><exploit>true</exploit><routes><route><to>F4</to><pheromoneTrail>2898.4390000000003</pheromoneTrail></route><route><to>D4</to><pheromoneTrail>2708.5400000000004</pheromoneTrail></route><route><to>G3</to><pheromoneTrail>2327.7591</pheromoneTrail></route><route><to>E4</to><pheromoneTrail>2224.8478000000005</pheromoneTrail></route><route><to>C4</to><pheromoneTrail>2161.2385000000004</pheromoneTrail></route></routes></PitchHistory><PitchHistory move="7"><to>F4</to><MusicThought>Complemental_ShortTerm</MusicThought><exploit>true</exploit><routes><route><to>E4</to><pheromoneTrail>3178.6711400000004</pheromoneTrail></route><route><to>A4</to><pheromoneTrail>2150.08814</pheromoneTrail></route><route><to>F4</to><pheromoneTrail>2086.14776</pheromoneTrail></route><route><to>G4</to><pheromoneTrail>1799.9018</pheromoneTrail></route></routes></PitchHistory><PitchHistory move="8"><to>G4</to><MusicThought>Directional_Conjunct</MusicThought><exploit>true</exploit><routes><route><to>G4</to><pheromoneTrail>12518.303547000003</pheromoneTrail></route></routes></PitchHistory><PitchHistory move="9"><to>A4</to><MusicThought>Directional_Conjunct</MusicThought><exploit>true</exploit><routes><route><to>A4</to><pheromoneTrail>5225.3013775</pheromoneTrail></route></routes></PitchHistory><PitchHistory move="10"><to>G4</to><MusicThought>Complemental_ShortTerm</MusicThought><exploit>true</exploit><routes><route><to>F4</to><pheromoneTrail>2610.96970727</pheromoneTrail></route><route><to>A3</to><pheromoneTrail>2455.04060281</pheromoneTrail></route><route><to>D4</to><pheromoneTrail>2356.7786685200003</pheromoneTrail></route><route><to>G4</to><pheromoneTrail>2355.3712956000004</pheromoneTrail></route><route><to>E4</to><pheromoneTrail>2293.10942573</pheromoneTrail></route></routes></PitchHistory><PitchHistory move="11"><to>A4</to><MusicThought>Complemental_ShortTerm</MusicThought><exploit>false</exploit><routes><route><to>A4</to><pheromoneTrail>4585.544115775</pheromoneTrail></route></routes></PitchHistory><PitchHistory move="12"><to>D4</to><MusicThought>Complemental_ShortTerm</MusicThought><exploit>false</exploit><routes><route><to>F4</to><pheromoneTrail>2321.1554628887</pheromoneTrail></route><route><to>A3</to><pheromoneTrail>2157.2728882761003</pheromoneTrail></route><route><to>G4</to><pheromoneTrail>2103.1707494360003</pheromoneTrail></route><route><to>D4</to><pheromoneTrail>2082.1107215012007</pheromoneTrail></route><route><to>E4</to><pheromoneTrail>2048.8186348413</pheromoneTrail></route></routes></PitchHistory><PitchHistory move="13"><to>F4</to><MusicThought>NULL</MusicThought><exploit>true</exploit><routes><route><to>F4</to><pheromoneTrail>0.0</pheromoneTrail></route></routes></PitchHistory><PitchHistory move="14"><to>E4</to><MusicThought>NULL</MusicThought><exploit>true</exploit><routes><route><to>E4</to><pheromoneTrail>0.0</pheromoneTrail></route></routes></PitchHistory></history></MusicThread>