<?xml version="1.0" encoding="UTF-8"?>
<MusicThread><mode>Ionian</mode><CantusFirmus>[C4, G4*, C4, D4, E4, F4, G4*, C4, F4, G4*, F4, E4, D4, C4]</CantusFirmus><middle>E4</middle><rating rate="100.0"><range>100.0</range><length>100.0</length><dominantCount>100.0</dominantCount></rating><history length="14"><PitchHistory move="1"><to>G4</to><MusicThought>Complemental_ShortTerm</MusicThought><exploit>true</exploit><routes><route><to>B3</to><pheromoneTrail>3603.0</pheromoneTrail></route><route><to>D4</to><pheromoneTrail>3512.0</pheromoneTrail></route><route><to>E4</to><pheromoneTrail>1306.0</pheromoneTrail></route><route><to>G4</to><pheromoneTrail>1108.0</pheromoneTrail></route><route><to>F3</to><pheromoneTrail>1063.0</pheromoneTrail></route><route><to>A3</to><pheromoneTrail>1043.0</pheromoneTrail></route><route><to>G3</to><pheromoneTrail>995.0</pheromoneTrail></route><route><to>F4</to><pheromoneTrail>913.0</pheromoneTrail></route></routes></PitchHistory><PitchHistory move="2"><to>C4</to><MusicThought>Complemental_ShortTerm</MusicThought><exploit>true</exploit><routes><route><to>E4</to><pheromoneTrail>255.0</pheromoneTrail></route><route><to>C4</to><pheromoneTrail>247.0</pheromoneTrail></route><route><to>D4</to><pheromoneTrail>232.0</pheromoneTrail></route><route><to>G3</to><pheromoneTrail>198.0</pheromoneTrail></route><route><to>F4</to><pheromoneTrail>176.0</pheromoneTrail></route></routes></PitchHistory><PitchHistory move="3"><to>D4</to><MusicThought>Complemental_ShortTerm</MusicThought><exploit>true</exploit><routes><route><to>D4</to><pheromoneTrail>10176.41</pheromoneTrail></route><route><to>E4</to><pheromoneTrail>3904.23</pheromoneTrail></route><route><to>G4</to><pheromoneTrail>3512.64</pheromoneTrail></route><route><to>F4</to><pheromoneTrail>3100.7300000000005</pheromoneTrail></route></routes></PitchHistory><PitchHistory move="4"><to>E4</to><MusicThought>Complemental_LongTerm</MusicThought><exploit>true</exploit><routes><route><to>E4</to><pheromoneTrail>3604.2000000000003</pheromoneTrail></route><route><to>F4</to><pheromoneTrail>1167.09</pheromoneTrail></route><route><to>G4</to><pheromoneTrail>1148.1000000000001</pheromoneTrail></route><route><to>A4</to><pheromoneTrail>947.91</pheromoneTrail></route></routes></PitchHistory><PitchHistory move="5"><to>F4</to><MusicThought>Directional_Conjunct</MusicThought><exploit>true</exploit><routes><route><to>F4</to><pheromoneTrail>2789.157</pheromoneTrail></route></routes></PitchHistory><PitchHistory move="6"><to>G4</to><MusicThought>Directional_Conjunct</MusicThought><exploit>false</exploit><routes><route><to>G4</to><pheromoneTrail>8917.427300000001</pheromoneTrail></route></routes></PitchHistory><PitchHistory move="7"><to>C4</to><MusicThought>Complemental_LongTerm</MusicThought><exploit>false</exploit><routes><route><to>F4</to><pheromoneTrail>3111.33334</pheromoneTrail></route><route><to>E4</to><pheromoneTrail>3078.647830000001</pheromoneTrail></route><route><to>C4</to><pheromoneTrail>2923.28791</pheromoneTrail></route><route><to>D4</to><pheromoneTrail>2865.6617400000005</pheromoneTrail></route><route><to>G3</to><pheromoneTrail>2811.40234</pheromoneTrail></route></routes></PitchHistory><PitchHistory move="8"><to>F4</to><MusicThought>Complemental_ShortTerm</MusicThought><exploit>true</exploit><routes><route><to>D4</to><pheromoneTrail>9898.8221109</pheromoneTrail></route><route><to>E4</to><pheromoneTrail>3831.9768127000007</pheromoneTrail></route><route><to>G4</to><pheromoneTrail>3625.6721036</pheromoneTrail></route><route><to>F4</to><pheromoneTrail>3251.9177777000004</pheromoneTrail></route></routes></PitchHistory><PitchHistory move="9"><to>G4</to><MusicThought>Directional_Conjunct</MusicThought><exploit>false</exploit><routes><route><to>G4</to><pheromoneTrail>11707.987501700001</pheromoneTrail></route></routes></PitchHistory><PitchHistory move="10"><to>F4</to><MusicThought>Complemental_LongTerm</MusicThought><exploit>true</exploit><routes><route><to>F4</to><pheromoneTrail>4253.606004860001</pheromoneTrail></route><route><to>E4</to><pheromoneTrail>3804.6692680700007</pheromoneTrail></route><route><to>C4</to><pheromoneTrail>3614.5678863900002</pheromoneTrail></route><route><to>D4</to><pheromoneTrail>3559.25340846</pheromoneTrail></route><route><to>G3</to><pheromoneTrail>3429.6103058600006</pheromoneTrail></route></routes></PitchHistory><PitchHistory move="11"><to>E4</to><MusicThought>Directional_Conjunct</MusicThought><exploit>true</exploit><routes><route><to>E4</to><pheromoneTrail>6912.9645785600005</pheromoneTrail></route></routes></PitchHistory><PitchHistory move="12"><to>D4</to><MusicThought>NULL</MusicThought><exploit>true</exploit><routes><route><to>D4</to><pheromoneTrail>0.0</pheromoneTrail></route></routes></PitchHistory><PitchHistory move="13"><to>C4</to><MusicThought>NULL</MusicThought><exploit>true</exploit><routes><route><to>C4</to><pheromoneTrail>0.0</pheromoneTrail></route></routes></PitchHistory></history></MusicThread>